<?xml version="1.0" encoding="utf-8"?>
<PermissionSets>
  <PermissionSet RoleID="APPXITE" RoleName="AppXite Permissions">
    <Permission>
      <ObjectType>5</ObjectType>
      <ObjectID>70155324</ObjectID>
      <ReadPermission>0</ReadPermission>
      <InsertPermission>0</InsertPermission>
      <ModifyPermission>0</ModifyPermission>
      <DeletePermission>0</DeletePermission>
      <ExecutePermission>1</ExecutePermission>
      <SecurityFilter />
    </Permission>
    <Permission>
      <ObjectType>5</ObjectType>
      <ObjectID>70155325</ObjectID>
      <ReadPermission>0</ReadPermission>
      <InsertPermission>0</InsertPermission>
      <ModifyPermission>0</ModifyPermission>
      <DeletePermission>0</DeletePermission>
      <ExecutePermission>1</ExecutePermission>
      <SecurityFilter />
    </Permission>
    <Permission>
      <ObjectType>5</ObjectType>
      <ObjectID>70155326</ObjectID>
      <ReadPermission>0</ReadPermission>
      <InsertPermission>0</InsertPermission>
      <ModifyPermission>0</ModifyPermission>
      <DeletePermission>0</DeletePermission>
      <ExecutePermission>1</ExecutePermission>
      <SecurityFilter />
    </Permission>
    <Permission>
      <ObjectType>5</ObjectType>
      <ObjectID>70155327</ObjectID>
      <ReadPermission>0</ReadPermission>
      <InsertPermission>0</InsertPermission>
      <ModifyPermission>0</ModifyPermission>
      <DeletePermission>0</DeletePermission>
      <ExecutePermission>1</ExecutePermission>
      <SecurityFilter />
    </Permission>
    <Permission>
      <ObjectType>5</ObjectType>
      <ObjectID>70155328</ObjectID>
      <ReadPermission>0</ReadPermission>
      <InsertPermission>0</InsertPermission>
      <ModifyPermission>0</ModifyPermission>
      <DeletePermission>0</DeletePermission>
      <ExecutePermission>1</ExecutePermission>
      <SecurityFilter />
    </Permission>
    <Permission>
      <ObjectType>5</ObjectType>
      <ObjectID>70155329</ObjectID>
      <ReadPermission>0</ReadPermission>
      <InsertPermission>0</InsertPermission>
      <ModifyPermission>0</ModifyPermission>
      <DeletePermission>0</DeletePermission>
      <ExecutePermission>1</ExecutePermission>
      <SecurityFilter />
    </Permission>
    <Permission>
      <ObjectType>5</ObjectType>
      <ObjectID>70155331</ObjectID>
      <ReadPermission>0</ReadPermission>
      <InsertPermission>0</InsertPermission>
      <ModifyPermission>0</ModifyPermission>
      <DeletePermission>0</DeletePermission>
      <ExecutePermission>1</ExecutePermission>
      <SecurityFilter />
    </Permission>
    <Permission>
      <ObjectType>5</ObjectType>
      <ObjectID>70155330</ObjectID>
      <ReadPermission>0</ReadPermission>
      <InsertPermission>0</InsertPermission>
      <ModifyPermission>0</ModifyPermission>
      <DeletePermission>0</DeletePermission>
      <ExecutePermission>1</ExecutePermission>
      <SecurityFilter />
    </Permission>
    <Permission>
      <ObjectType>0</ObjectType>
      <ObjectID>70155328</ObjectID>
      <ReadPermission>1</ReadPermission>
      <InsertPermission>1</InsertPermission>
      <ModifyPermission>1</ModifyPermission>
      <DeletePermission>1</DeletePermission>
      <ExecutePermission>0</ExecutePermission>
      <SecurityFilter />
    </Permission>
    <Permission>
      <ObjectType>1</ObjectType>
      <ObjectID>70155328</ObjectID>
      <ReadPermission>0</ReadPermission>
      <InsertPermission>0</InsertPermission>
      <ModifyPermission>0</ModifyPermission>
      <DeletePermission>0</DeletePermission>
      <ExecutePermission>1</ExecutePermission>
      <SecurityFilter />
    </Permission>
    <Permission>
      <ObjectType>0</ObjectType>
      <ObjectID>70155324</ObjectID>
      <ReadPermission>1</ReadPermission>
      <InsertPermission>1</InsertPermission>
      <ModifyPermission>1</ModifyPermission>
      <DeletePermission>1</DeletePermission>
      <ExecutePermission>0</ExecutePermission>
      <SecurityFilter />
    </Permission>
    <Permission>
      <ObjectType>1</ObjectType>
      <ObjectID>70155324</ObjectID>
      <ReadPermission>0</ReadPermission>
      <InsertPermission>0</InsertPermission>
      <ModifyPermission>0</ModifyPermission>
      <DeletePermission>0</DeletePermission>
      <ExecutePermission>1</ExecutePermission>
      <SecurityFilter />
    </Permission>
    <Permission>
      <ObjectType>0</ObjectType>
      <ObjectID>70155325</ObjectID>
      <ReadPermission>1</ReadPermission>
      <InsertPermission>1</InsertPermission>
      <ModifyPermission>1</ModifyPermission>
      <DeletePermission>1</DeletePermission>
      <ExecutePermission>0</ExecutePermission>
      <SecurityFilter />
    </Permission>
    <Permission>
      <ObjectType>1</ObjectType>
      <ObjectID>70155325</ObjectID>
      <ReadPermission>0</ReadPermission>
      <InsertPermission>0</InsertPermission>
      <ModifyPermission>0</ModifyPermission>
      <DeletePermission>0</DeletePermission>
      <ExecutePermission>1</ExecutePermission>
      <SecurityFilter />
    </Permission>
    <Permission>
      <ObjectType>0</ObjectType>
      <ObjectID>70155326</ObjectID>
      <ReadPermission>1</ReadPermission>
      <InsertPermission>1</InsertPermission>
      <ModifyPermission>1</ModifyPermission>
      <DeletePermission>1</DeletePermission>
      <ExecutePermission>0</ExecutePermission>
      <SecurityFilter />
    </Permission>
    <Permission>
      <ObjectType>1</ObjectType>
      <ObjectID>70155326</ObjectID>
      <ReadPermission>0</ReadPermission>
      <InsertPermission>0</InsertPermission>
      <ModifyPermission>0</ModifyPermission>
      <DeletePermission>0</DeletePermission>
      <ExecutePermission>1</ExecutePermission>
      <SecurityFilter />
    </Permission>
    <Permission>
      <ObjectType>0</ObjectType>
      <ObjectID>70155327</ObjectID>
      <ReadPermission>1</ReadPermission>
      <InsertPermission>1</InsertPermission>
      <ModifyPermission>1</ModifyPermission>
      <DeletePermission>1</DeletePermission>
      <ExecutePermission>0</ExecutePermission>
      <SecurityFilter />
    </Permission>
    <Permission>
      <ObjectType>1</ObjectType>
      <ObjectID>70155327</ObjectID>
      <ReadPermission>0</ReadPermission>
      <InsertPermission>0</InsertPermission>
      <ModifyPermission>0</ModifyPermission>
      <DeletePermission>0</DeletePermission>
      <ExecutePermission>1</ExecutePermission>
      <SecurityFilter />
    </Permission>
    <Permission>
      <ObjectType>0</ObjectType>
      <ObjectID>70155329</ObjectID>
      <ReadPermission>1</ReadPermission>
      <InsertPermission>1</InsertPermission>
      <ModifyPermission>1</ModifyPermission>
      <DeletePermission>1</DeletePermission>
      <ExecutePermission>0</ExecutePermission>
      <SecurityFilter />
    </Permission>
    <Permission>
      <ObjectType>1</ObjectType>
      <ObjectID>70155329</ObjectID>
      <ReadPermission>0</ReadPermission>
      <InsertPermission>0</InsertPermission>
      <ModifyPermission>0</ModifyPermission>
      <DeletePermission>0</DeletePermission>
      <ExecutePermission>1</ExecutePermission>
      <SecurityFilter />
    </Permission>
    <Permission>
      <ObjectType>0</ObjectType>
      <ObjectID>70155332</ObjectID>
      <ReadPermission>1</ReadPermission>
      <InsertPermission>1</InsertPermission>
      <ModifyPermission>1</ModifyPermission>
      <DeletePermission>1</DeletePermission>
      <ExecutePermission>0</ExecutePermission>
      <SecurityFilter />
    </Permission>
    <Permission>
      <ObjectType>1</ObjectType>
      <ObjectID>70155332</ObjectID>
      <ReadPermission>0</ReadPermission>
      <InsertPermission>0</InsertPermission>
      <ModifyPermission>0</ModifyPermission>
      <DeletePermission>0</DeletePermission>
      <ExecutePermission>1</ExecutePermission>
      <SecurityFilter />
    </Permission>
    <Permission>
      <ObjectType>0</ObjectType>
      <ObjectID>70155333</ObjectID>
      <ReadPermission>1</ReadPermission>
      <InsertPermission>1</InsertPermission>
      <ModifyPermission>1</ModifyPermission>
      <DeletePermission>1</DeletePermission>
      <ExecutePermission>0</ExecutePermission>
      <SecurityFilter />
    </Permission>
    <Permission>
      <ObjectType>1</ObjectType>
      <ObjectID>70155333</ObjectID>
      <ReadPermission>0</ReadPermission>
      <InsertPermission>0</InsertPermission>
      <ModifyPermission>0</ModifyPermission>
      <DeletePermission>0</DeletePermission>
      <ExecutePermission>1</ExecutePermission>
      <SecurityFilter />
    </Permission>
    <Permission>
      <ObjectType>0</ObjectType>
      <ObjectID>70155334</ObjectID>
      <ReadPermission>1</ReadPermission>
      <InsertPermission>1</InsertPermission>
      <ModifyPermission>1</ModifyPermission>
      <DeletePermission>1</DeletePermission>
      <ExecutePermission>0</ExecutePermission>
      <SecurityFilter />
    </Permission>
    <Permission>
      <ObjectType>1</ObjectType>
      <ObjectID>70155334</ObjectID>
      <ReadPermission>0</ReadPermission>
      <InsertPermission>0</InsertPermission>
      <ModifyPermission>0</ModifyPermission>
      <DeletePermission>0</DeletePermission>
      <ExecutePermission>1</ExecutePermission>
      <SecurityFilter />
    </Permission>
    <Permission>
      <ObjectType>8</ObjectType>
      <ObjectID>70155331</ObjectID>
      <ReadPermission>0</ReadPermission>
      <InsertPermission>0</InsertPermission>
      <ModifyPermission>0</ModifyPermission>
      <DeletePermission>0</DeletePermission>
      <ExecutePermission>1</ExecutePermission>
      <SecurityFilter />
    </Permission>
    <Permission>
      <ObjectType>8</ObjectType>
      <ObjectID>70155338</ObjectID>
      <ReadPermission>0</ReadPermission>
      <InsertPermission>0</InsertPermission>
      <ModifyPermission>0</ModifyPermission>
      <DeletePermission>0</DeletePermission>
      <ExecutePermission>1</ExecutePermission>
      <SecurityFilter />
    </Permission>
    <Permission>
      <ObjectType>8</ObjectType>
      <ObjectID>70155328</ObjectID>
      <ReadPermission>0</ReadPermission>
      <InsertPermission>0</InsertPermission>
      <ModifyPermission>0</ModifyPermission>
      <DeletePermission>0</DeletePermission>
      <ExecutePermission>1</ExecutePermission>
      <SecurityFilter />
    </Permission>
    <Permission>
      <ObjectType>8</ObjectType>
      <ObjectID>70155324</ObjectID>
      <ReadPermission>0</ReadPermission>
      <InsertPermission>0</InsertPermission>
      <ModifyPermission>0</ModifyPermission>
      <DeletePermission>0</DeletePermission>
      <ExecutePermission>1</ExecutePermission>
      <SecurityFilter />
    </Permission>
    <Permission>
      <ObjectType>8</ObjectType>
      <ObjectID>70155327</ObjectID>
      <ReadPermission>0</ReadPermission>
      <InsertPermission>0</InsertPermission>
      <ModifyPermission>0</ModifyPermission>
      <DeletePermission>0</DeletePermission>
      <ExecutePermission>1</ExecutePermission>
      <SecurityFilter />
    </Permission>
    <Permission>
      <ObjectType>8</ObjectType>
      <ObjectID>70155329</ObjectID>
      <ReadPermission>0</ReadPermission>
      <InsertPermission>0</InsertPermission>
      <ModifyPermission>0</ModifyPermission>
      <DeletePermission>0</DeletePermission>
      <ExecutePermission>1</ExecutePermission>
      <SecurityFilter />
    </Permission>
    <Permission>
      <ObjectType>8</ObjectType>
      <ObjectID>70155330</ObjectID>
      <ReadPermission>0</ReadPermission>
      <InsertPermission>0</InsertPermission>
      <ModifyPermission>0</ModifyPermission>
      <DeletePermission>0</DeletePermission>
      <ExecutePermission>1</ExecutePermission>
      <SecurityFilter />
    </Permission>
    <Permission>
      <ObjectType>8</ObjectType>
      <ObjectID>70155332</ObjectID>
      <ReadPermission>0</ReadPermission>
      <InsertPermission>0</InsertPermission>
      <ModifyPermission>0</ModifyPermission>
      <DeletePermission>0</DeletePermission>
      <ExecutePermission>1</ExecutePermission>
      <SecurityFilter />
    </Permission>
    <Permission>
      <ObjectType>8</ObjectType>
      <ObjectID>70155333</ObjectID>
      <ReadPermission>0</ReadPermission>
      <InsertPermission>0</InsertPermission>
      <ModifyPermission>0</ModifyPermission>
      <DeletePermission>0</DeletePermission>
      <ExecutePermission>1</ExecutePermission>
      <SecurityFilter />
    </Permission>
    <Permission>
      <ObjectType>8</ObjectType>
      <ObjectID>70155334</ObjectID>
      <ReadPermission>0</ReadPermission>
      <InsertPermission>0</InsertPermission>
      <ModifyPermission>0</ModifyPermission>
      <DeletePermission>0</DeletePermission>
      <ExecutePermission>1</ExecutePermission>
      <SecurityFilter />
    </Permission>
    <Permission>
      <ObjectType>8</ObjectType>
      <ObjectID>70155335</ObjectID>
      <ReadPermission>0</ReadPermission>
      <InsertPermission>0</InsertPermission>
      <ModifyPermission>0</ModifyPermission>
      <DeletePermission>0</DeletePermission>
      <ExecutePermission>1</ExecutePermission>
      <SecurityFilter />
    </Permission>
    <Permission>
      <ObjectType>8</ObjectType>
      <ObjectID>70155336</ObjectID>
      <ReadPermission>0</ReadPermission>
      <InsertPermission>0</InsertPermission>
      <ModifyPermission>0</ModifyPermission>
      <DeletePermission>0</DeletePermission>
      <ExecutePermission>1</ExecutePermission>
      <SecurityFilter />
    </Permission>
    <Permission>
      <ObjectType>8</ObjectType>
      <ObjectID>70155337</ObjectID>
      <ReadPermission>0</ReadPermission>
      <InsertPermission>0</InsertPermission>
      <ModifyPermission>0</ModifyPermission>
      <DeletePermission>0</DeletePermission>
      <ExecutePermission>1</ExecutePermission>
      <SecurityFilter />
    </Permission>
    <Permission>
      <ObjectType>8</ObjectType>
      <ObjectID>70155339</ObjectID>
      <ReadPermission>0</ReadPermission>
      <InsertPermission>0</InsertPermission>
      <ModifyPermission>0</ModifyPermission>
      <DeletePermission>0</DeletePermission>
      <ExecutePermission>1</ExecutePermission>
      <SecurityFilter />
    </Permission>
    <Permission>
      <ObjectType>8</ObjectType>
      <ObjectID>70155325</ObjectID>
      <ReadPermission>0</ReadPermission>
      <InsertPermission>0</InsertPermission>
      <ModifyPermission>0</ModifyPermission>
      <DeletePermission>0</DeletePermission>
      <ExecutePermission>1</ExecutePermission>
      <SecurityFilter />
    </Permission>
    <Permission>
      <ObjectType>8</ObjectType>
      <ObjectID>70155326</ObjectID>
      <ReadPermission>0</ReadPermission>
      <InsertPermission>0</InsertPermission>
      <ModifyPermission>0</ModifyPermission>
      <DeletePermission>0</DeletePermission>
      <ExecutePermission>1</ExecutePermission>
      <SecurityFilter />
    </Permission>
    <Permission>
      <ObjectType>3</ObjectType>
      <ObjectID>70155324</ObjectID>
      <ReadPermission>0</ReadPermission>
      <InsertPermission>0</InsertPermission>
      <ModifyPermission>0</ModifyPermission>
      <DeletePermission>0</DeletePermission>
      <ExecutePermission>1</ExecutePermission>
      <SecurityFilter />
    </Permission>
    <Permission>
      <ObjectType>3</ObjectType>
      <ObjectID>70155325</ObjectID>
      <ReadPermission>0</ReadPermission>
      <InsertPermission>0</InsertPermission>
      <ModifyPermission>0</ModifyPermission>
      <DeletePermission>0</DeletePermission>
      <ExecutePermission>1</ExecutePermission>
      <SecurityFilter />
    </Permission>
    <Permission>
      <ObjectType>3</ObjectType>
      <ObjectID>70155326</ObjectID>
      <ReadPermission>0</ReadPermission>
      <InsertPermission>0</InsertPermission>
      <ModifyPermission>0</ModifyPermission>
      <DeletePermission>0</DeletePermission>
      <ExecutePermission>1</ExecutePermission>
      <SecurityFilter />
    </Permission>
    <Permission>
      <ObjectType>3</ObjectType>
      <ObjectID>70155328</ObjectID>
      <ReadPermission>0</ReadPermission>
      <InsertPermission>0</InsertPermission>
      <ModifyPermission>0</ModifyPermission>
      <DeletePermission>0</DeletePermission>
      <ExecutePermission>1</ExecutePermission>
      <SecurityFilter />
    </Permission>
    <Permission>
      <ObjectType>3</ObjectType>
      <ObjectID>70155330</ObjectID>
      <ReadPermission>0</ReadPermission>
      <InsertPermission>0</InsertPermission>
      <ModifyPermission>0</ModifyPermission>
      <DeletePermission>0</DeletePermission>
      <ExecutePermission>1</ExecutePermission>
      <SecurityFilter />
    </Permission>
    <Permission>
      <ObjectType>3</ObjectType>
      <ObjectID>70155331</ObjectID>
      <ReadPermission>0</ReadPermission>
      <InsertPermission>0</InsertPermission>
      <ModifyPermission>0</ModifyPermission>
      <DeletePermission>0</DeletePermission>
      <ExecutePermission>1</ExecutePermission>
      <SecurityFilter />
    </Permission>
    <Permission>
      <ObjectType>3</ObjectType>
      <ObjectID>70155332</ObjectID>
      <ReadPermission>0</ReadPermission>
      <InsertPermission>0</InsertPermission>
      <ModifyPermission>0</ModifyPermission>
      <DeletePermission>0</DeletePermission>
      <ExecutePermission>1</ExecutePermission>
      <SecurityFilter />
    </Permission>
    <Permission>
      <ObjectType>3</ObjectType>
      <ObjectID>70155333</ObjectID>
      <ReadPermission>0</ReadPermission>
      <InsertPermission>0</InsertPermission>
      <ModifyPermission>0</ModifyPermission>
      <DeletePermission>0</DeletePermission>
      <ExecutePermission>1</ExecutePermission>
      <SecurityFilter />
    </Permission>
    <Permission>
      <ObjectType>3</ObjectType>
      <ObjectID>70155340</ObjectID>
      <ReadPermission>0</ReadPermission>
      <InsertPermission>0</InsertPermission>
      <ModifyPermission>0</ModifyPermission>
      <DeletePermission>0</DeletePermission>
      <ExecutePermission>1</ExecutePermission>
      <SecurityFilter />
    </Permission>
    <Permission>
      <ObjectType>3</ObjectType>
      <ObjectID>70155341</ObjectID>
      <ReadPermission>0</ReadPermission>
      <InsertPermission>0</InsertPermission>
      <ModifyPermission>0</ModifyPermission>
      <DeletePermission>0</DeletePermission>
      <ExecutePermission>1</ExecutePermission>
      <SecurityFilter />
    </Permission>
    <Permission>
      <ObjectType>3</ObjectType>
      <ObjectID>70155342</ObjectID>
      <ReadPermission>0</ReadPermission>
      <InsertPermission>0</InsertPermission>
      <ModifyPermission>0</ModifyPermission>
      <DeletePermission>0</DeletePermission>
      <ExecutePermission>1</ExecutePermission>
      <SecurityFilter />
    </Permission>
    <Permission>
      <ObjectType>3</ObjectType>
      <ObjectID>70155344</ObjectID>
      <ReadPermission>0</ReadPermission>
      <InsertPermission>0</InsertPermission>
      <ModifyPermission>0</ModifyPermission>
      <DeletePermission>0</DeletePermission>
      <ExecutePermission>1</ExecutePermission>
      <SecurityFilter />
    </Permission>
  </PermissionSet>
</PermissionSets>